{"xcat1":"DIY电脑","products":[{"id":"catalog-16109378213","title":"【百亿补贴】宁美龙魂i5 14400F/14600KF/RTX5060Ti三角洲游戏电脑主机办公台式diy整机电竞海景房全套组装机","category":"DIY兼容机","xcat1":"DIY电脑","xcat2":"DIY兼容机","price":4559.0,"image":"https://img.alicdn.com/imgextra/i4/595397331/O1CN01LMk8AW241ei6wtnCA_!!4611686018427382483-0-item_pic.jpg","ordercost":605395.0,"sales":"605,395人收藏","attributes":["DIY电脑","DIY兼容机","台式机"],"baseScore":605395.0,"novelty":0,"brand":"淘宝","origin":"","audiences":[],"styles":[],"goals":[],"trend":0},{"id":"catalog-574977772301","title":"水冷i7八核高端家用游戏型吃鸡DIY组装电脑主机台式全套高配整机","category":"DIY兼容机","xcat1":"DIY电脑","xcat2":"DIY兼容机","price":1788.0,"image":"https://img.alicdn.com/imgextra/i3/3034987077/O1CN01ZewCv0229K0B2KbhV_!!3034987077.jpg","ordercost":598746.0,"sales":"598,746人收藏","attributes":["DIY电脑","DIY兼容机","台式机"],"baseScore":598746.0,"novelty":0,"brand":"淘宝","origin":"","audiences":[],"styles":[],"goals":[],"trend":0},{"id":"catalog-17019553913","title":"【百亿补贴】京天华盛I5 14401TEF/RTX5060Ti/3050/5050/5060三角洲游戏电脑主机办公台式机整机DIY组装机","category":"DIY兼容机","xcat1":"DIY电脑","xcat2":"DIY兼容机","price":3399.0,"image":"https://img.alicdn.com/imgextra/i4/1097280647/O1CN01cgoOrK1GeNP6j9SAM_!!4611686018427382919-0-item_pic.jpg","ordercost":597249.0,"sales":"597,249人收藏","attributes":["DIY电脑","DIY兼容机","台式机"],"baseScore":597249.0,"novelty":0,"brand":"淘宝","origin":"","audiences":[],"styles":[],"goals":[],"trend":0},{"id":"catalog-520149040205","title":"【国家补贴】华硕海景房电脑主机i5 14400F/14600KF/i9/RTX5060Ti/5070整机家用游戏diy组装电脑台式电脑","category":"DIY兼容机","xcat1":"DIY电脑","xcat2":"DIY兼容机","price":5777.0,"image":"https://img.alicdn.com/imgextra/i1/1652528654/O1CN01Brs1db2DnahuvOAGJ_!!4611686018427385358-0-item_pic.jpg","ordercost":418372.0,"sales":"418,372人收藏","attributes":["DIY电脑","DIY兼容机","台式机"],"baseScore":418372.0,"novelty":0,"brand":"淘宝","origin":"","audiences":[],"styles":[],"goals":[],"trend":0},{"id":"catalog-537053661486","title":"高配办公家用游戏一体机电脑十核i7超薄台式主机整机独显全套吃鸡","category":"DIY兼容机","xcat1":"DIY电脑","xcat2":"DIY兼容机","price":1898.0,"image":"https://img.alicdn.com/imgextra/i3/124869574/O1CN01z6pzXf2Kawn67h6Eo_!!124869574.jpg","ordercost":297958.0,"sales":"297,958人收藏","attributes":["DIY电脑","DIY兼容机","台式机"],"baseScore":297958.0,"novelty":0,"brand":"淘宝","origin":"","audiences":[],"styles":[],"goals":[],"trend":0},{"id":"catalog-619418503971","title":"组装电脑台式全套高配主机游戏型吃鸡RTX2060/i7网吧办公家用组合","category":"DIY兼容机","xcat1":"DIY电脑","xcat2":"DIY兼容机","price":2399.0,"image":"https://img.alicdn.com/imgextra/i1/886445548/O1CN01XslzUi1qr2TsLbsZS_!!886445548.png","ordercost":195132.0,"sales":"195,132人收藏","attributes":["DIY电脑","DIY兼容机","台式机"],"baseScore":195132.0,"novelty":0,"brand":"淘宝","origin":"","audiences":[],"styles":[],"goals":[],"trend":0},{"id":"catalog-37564253018","title":"【林树推荐+政府补贴】名龙堂台式电脑265KF/14600KF/14700F/RTX5060/5060Ti 2K主机直播DIY电脑组装机三角洲","category":"DIY兼容机","xcat1":"DIY电脑","xcat2":"DIY兼容机","price":10499.0,"image":"https://img.alicdn.com/imgextra/i4/931421195/O1CN01LbOuiT1KhMS8RlDMP_!!4611686018427386891-0-item_pic.jpg","ordercost":190222.0,"sales":"190,222人收藏","attributes":["DIY电脑","DIY兼容机","台式机"],"baseScore":190222.0,"novelty":0,"brand":"淘宝","origin":"","audiences":[],"styles":[],"goals":[],"trend":0},{"id":"catalog-569538460316","title":"i5高配i7独显吃鸡游戏DIY电脑主机gta5组装台式电脑整机送24英寸全套","category":"DIY兼容机","xcat1":"DIY电脑","xcat2":"DIY兼容机","price":3099.0,"image":"https://img.alicdn.com/imgextra/i1/687499522/O1CN01RqQxuk2KD8Er2eJIY_!!0-item_pic.jpg","ordercost":114558.0,"sales":"114,558人收藏","attributes":["DIY电脑","DIY兼容机","台式机"],"baseScore":114558.0,"novelty":0,"brand":"淘宝","origin":"","audiences":[],"styles":[],"goals":[],"trend":0},{"id":"catalog-588575917857","title":"12400F/14600K/5060TI/5070整机直播设计/三角洲无畏契约电脑主机","category":"DIY兼容机","xcat1":"DIY电脑","xcat2":"DIY兼容机","price":3000.0,"image":"https://img.alicdn.com/imgextra/i1/164998637/O1CN01sfBeAh2DfnxjEkMGG_!!164998637.jpg","ordercost":87809.0,"sales":"87,809人收藏","attributes":["DIY电脑","DIY兼容机","台式机"],"baseScore":87809.0,"novelty":0,"brand":"淘宝","origin":"","audiences":[],"styles":[],"goals":[],"trend":0},{"id":"catalog-625519251062","title":"【亮子装机】高端定制台式机游戏电脑主机整机DIY组装高配三角洲","category":"DIY兼容机","xcat1":"DIY电脑","xcat2":"DIY兼容机","price":3000.0,"image":"https://img.alicdn.com/imgextra/i3/2591435335/O1CN01Q9kKDx1pHU9d7KfWu_!!4611686018427382343-0-item_pic.jpg","ordercost":83560.0,"sales":"83,560人收藏","attributes":["DIY电脑","DIY兼容机","台式机"],"baseScore":83560.0,"novelty":0,"brand":"淘宝","origin":"","audiences":[],"styles":[],"goals":[],"trend":0},{"id":"catalog-544788589812","title":"老方至强e5电脑主机2696V4游戏工作室模拟器多开V3双路服务器装机","category":"DIY兼容机","xcat1":"DIY电脑","xcat2":"DIY兼容机","price":1725.0,"image":"https://img.alicdn.com/imgextra/i4/52434264/O1CN01jhwKnG1hMxvp3IWRe_!!52434264.jpg","ordercost":77787.0,"sales":"77,787人收藏","attributes":["DIY电脑","DIY兼容机","台式机"],"baseScore":77787.0,"novelty":0,"brand":"淘宝","origin":"","audiences":[],"styles":[],"goals":[],"trend":0},{"id":"catalog-628281669971","title":"七彩虹RTX5060/5050独显+英特尔18核36线程台式电脑i5/i7/i9主机","category":"DIY兼容机","xcat1":"DIY电脑","xcat2":"DIY兼容机","price":1488.0,"image":"https://img.alicdn.com/imgextra/i1/2208317651162/O1CN01Qd4FMo1KSFKTBhyDj_!!2208317651162.jpg","ordercost":60758.0,"sales":"60,758人收藏","attributes":["DIY电脑","DIY兼容机","台式机"],"baseScore":60758.0,"novelty":0,"brand":"淘宝","origin":"","audiences":[],"styles":[],"goals":[],"trend":0},{"id":"catalog-569623950738","title":"【敌鸽618】一台美好的AI游戏台式机 券补大促推荐配置单","category":"DIY兼容机","xcat1":"DIY电脑","xcat2":"DIY兼容机","price":1000.0,"image":"https://img.alicdn.com/imgextra/i4/2770614950/O1CN01Q1ZqfE1mR9foOSGo0_!!2770614950.png","ordercost":56889.0,"sales":"56,889人收藏","attributes":["DIY电脑","DIY兼容机","台式机"],"baseScore":56889.0,"novelty":0,"brand":"淘宝","origin":"","audiences":[],"styles":[],"goals":[],"trend":0},{"id":"catalog-618220910477","title":"【i5主流电竞】13400EF/14490F/4060TI/5060台式组装电脑主机高配电竞游戏三角洲直播设计师DIY兼容机全套","category":"DIY兼容机","xcat1":"DIY电脑","xcat2":"DIY兼容机","price":6999.0,"image":"https://img.alicdn.com/imgextra/i1/1125071973/O1CN0148Xe7v1QRgYF4Fv21_!!4611686018427386981-0-item_pic.jpg","ordercost":46184.0,"sales":"46,184人收藏","attributes":["DIY电脑","DIY兼容机","台式机"],"baseScore":46184.0,"novelty":0,"brand":"淘宝","origin":"","audiences":[],"styles":[],"goals":[],"trend":0},{"id":"catalog-678727712496","title":"华硕i5 14600KF/RTX5060主机5060TI电脑游戏直播设计台式组装整机","category":"DIY兼容机","xcat1":"DIY电脑","xcat2":"DIY兼容机","price":3299.0,"image":"https://img.alicdn.com/imgextra/i2/210209508/O1CN01lnJY6i2K6iwMRDDJ4_!!210209508.jpg","ordercost":44418.0,"sales":"44,418人收藏","attributes":["DIY电脑","DIY兼容机","台式机"],"baseScore":44418.0,"novelty":0,"brand":"淘宝","origin":"","audiences":[],"styles":[],"goals":[],"trend":0},{"id":"catalog-527000036834","title":"i5 12600KF/RTX5060 8G独显吃鸡永劫悟空赛博朋克DIY台式电脑主机","category":"DIY兼容机","xcat1":"DIY电脑","xcat2":"DIY兼容机","price":4799.0,"image":"https://img.alicdn.com/imgextra/i4/1628516818/O1CN010UDqMk20EhV6p8bH4_!!1628516818.jpg","ordercost":43374.0,"sales":"43,374人收藏","attributes":["DIY电脑","DIY兼容机","台式机"],"baseScore":43374.0,"novelty":0,"brand":"淘宝","origin":"","audiences":[],"styles":[],"goals":[],"trend":0},{"id":"catalog-21617595107","title":"环球盛达酷睿i3 4170/8G主机组装电脑整机 台式机组装机DIY兼容机","category":"DIY兼容机","xcat1":"DIY电脑","xcat2":"DIY兼容机","price":2688.0,"image":"https://img.alicdn.com/imgextra/i4/TB1UF9ILpXXXXaGXpXXXXXXXXXX_!!0-item_pic.jpg","ordercost":42506.0,"sales":"42,506人收藏","attributes":["DIY电脑","DIY兼容机","台式机"],"baseScore":42506.0,"novelty":0,"brand":"淘宝","origin":"","audiences":[],"styles":[],"goals":[],"trend":0},{"id":"catalog-42931853150","title":"手提便捷志强e5主机梦幻西游8开电脑大话西游办公家用水冷组装机","category":"DIY兼容机","xcat1":"DIY电脑","xcat2":"DIY兼容机","price":628.0,"image":"https://img.alicdn.com/imgextra/i4/273159481/O1CN01TuMmyH2JuME5ys6iU_!!273159481.jpg","ordercost":42406.0,"sales":"42,406人收藏","attributes":["DIY电脑","DIY兼容机","台式机"],"baseScore":42406.0,"novelty":0,"brand":"淘宝","origin":"","audiences":[],"styles":[],"goals":[],"trend":0},{"id":"catalog-43018200374","title":"i5四八核办公全套电脑主机台式电脑整机组装DIY兼容机商务家用","category":"DIY兼容机","xcat1":"DIY电脑","xcat2":"DIY兼容机","price":698.0,"image":"https://img.alicdn.com/imgextra/i2/835531891/O1CN012aUz5D1Pq85kNK7sk_!!835531891.jpg","ordercost":41948.0,"sales":"41,948人收藏","attributes":["DIY电脑","DIY兼容机","台式机"],"baseScore":41948.0,"novelty":0,"brand":"淘宝","origin":"","audiences":[],"styles":[],"goals":[],"trend":0}]}
